tmdeditor/__init__.py
tmdeditor/func_content_widget.py
tmdeditor/func_edge.py
tmdeditor/func_edge_dragging.py
tmdeditor/func_edge_intersect.py
tmdeditor/func_edge_rerouting.py
tmdeditor/func_edge_snapping.py
tmdeditor/func_edge_validators.py
tmdeditor/func_node.py
tmdeditor/func_scene.py
tmdeditor/func_scene_clipboard.py
tmdeditor/func_scene_history.py
tmdeditor/func_serialization.py
tmdeditor/func_socket.py
tmdeditor/graphical_cutline.py
tmdeditor/graphical_edge.py
tmdeditor/graphical_edge_types.py
tmdeditor/graphical_node.py
tmdeditor/graphical_scene.py
tmdeditor/graphical_socket.py
tmdeditor/graphical_view.py
tmdeditor/home_widget.py
tmdeditor/home_window.py
tmdeditor/utils.py
tmdeditor/utils_no_qt.py
tmd_editor-0.0.10.dist-info/METADATA
tmd_editor-0.0.10.dist-info/WHEEL
tmd_editor-0.0.10.dist-info/top_level.txt
tmd_editor-0.0.10.dist-info/RECORD
