Metadata-Version: 2.1
Name: tmd-editor
Version: 0.0.10
Summary: A Node Editor Library using PyQt5 Specialized in TMD
Author: DigiBrain4
Keywords: python,node,tmd_nodeeditor,editor,edges,sockets
Classifier: Intended Audience :: Developers
Classifier: Programming Language :: Python :: 3
Classifier: Operating System :: Microsoft :: Windows
Requires-Dist: PyQt5
Requires-Dist: QtPy
